csv_streamer/__init__.py
csv_streamer/csv_streamer.py
csv_streamer/zipzip.py
csv_streamer-0.1.0.dist-info/METADATA
csv_streamer-0.1.0.dist-info/WHEEL
csv_streamer-0.1.0.dist-info/licenses/LICENSE
csv_streamer-0.1.0.dist-info/RECORD
