Metadata-Version: 2.4
Name: csv-streamer
Version: 0.1.0
Summary: Stream CSV files (including from ZIP archives) as Arrow tables
Project-URL: Homepage, https://github.com/CHRISCARLON/csv-streamer
Project-URL: Repository, https://github.com/CHRISCARLON/csv-streamer
Project-URL: Issues, https://github.com/CHRISCARLON/csv-streamer/issues
Author: Chris Carlon
License-Expression: MIT
License-File: LICENSE
Keywords: arrow,csv,data,pyarrow,streaming
Requires-Python: >=3.12
Requires-Dist: pyarrow>=22.0.0
Requires-Dist: requests>=2.32.5
